{
  "error": false,
  "packages": 2465110,
  "last": 24974849,
  "latest": 24993293,
  "runs": {
    "total": 1021,
    "status": {
      "init": 896,
      "timeout": 74,
      "killed": 50,
      "restart": 1
    }
  },
  "repos": {
    "unsets": 977573,
    "github": 1457800,
    "gitlab": 5484,
    "bitbucket": 1358,
    "others": 22895
  },
  "stats": {
    "changes": 14100047,
    "inserts": 3371873,
    "updates": 8916215,
    "deletes": 1497201,
    "invalid": 314758,
    "ignored": 5
  },
  "batch": {
    "status": "init",
    "limit": 1,
    "since": 24974848,
    "index": 24974849,
    "until": 24974849,
    "started": "2023-07-16T12:05:10.433Z",
    "finished": "2023-07-16T12:19:23.170Z",
    "took_ms": 852737,
    "found": 1
  },
  "ignored": [
    20012191,
    20468062,
    20908815,
    21553560,
    21660508
  ]
}