{
  "packages": 981438,
  "last": 11360768,
  "latest": 11360768,
  "runs": {
    "total": 931,
    "status": {
      "restart": 4,
      "timeout": 69,
      "ok": 235,
      "killed": 623
    }
  },
  "repos": {
    "github": 965481,
    "gitlab": 3517,
    "bitbucket": 1180,
    "others": 11260
  },
  "stats": {
    "changes": 3990871,
    "inserts": 993752,
    "updates": 1592878,
    "deletes": 100526,
    "invalid": 1303715,
    "ignored": 14
  },
  "batch": {
    "limit": 17953,
    "since": 11342815,
    "index": 11360768,
    "until": 11360768,
    "started": "2021-01-22T17:04:14.691Z",
    "finished": "2021-01-22T21:52:09.392Z",
    "took_ms": 17274701,
    "found": 9536,
    "status": "ok"
  },
  "ignored": [
    2817133,
    2817134,
    5863655,
    5891749,
    6147589,
    6207043,
    6262717,
    6408267,
    6408268,
    6597446,
    6815143,
    6946259,
    7075370,
    7353196
  ]
}