{
  "packages": 843264,
  "last": 6094027,
  "latest": 6109993,
  "runs": {
    "total": 91,
    "status": {
      "restart": 4,
      "timeout": 22,
      "ok": 11,
      "killed": 54
    }
  },
  "repos": {
    "github": 830649,
    "gitlab": 2869,
    "bitbucket": 1060,
    "others": 8686
  },
  "stats": {
    "changes": 1476144,
    "inserts": 844254,
    "updates": 118483,
    "deletes": 46686,
    "invalid": 466721,
    "ignored": 4
  },
  "batch": {
    "limit": 15966,
    "since": 6094027,
    "index": 6094027,
    "until": 6109993,
    "started": "2020-04-16T00:11:23.211Z",
    "finished": "2020-04-16T05:11:59.971Z",
    "took_ms": 18036760,
    "found": 0,
    "status": "killed"
  },
  "ignored": [
    2817133,
    2817134,
    5863655,
    5891749
  ]
}