{
  "packages": 1116417,
  "last": 2770275,
  "latest": 2778794,
  "error": true,
  "runs": {
    "total": 54,
    "status": {
      "ok": 1,
      "restart": 0,
      "timeout": 3,
      "killed": 26,
      "init": 24
    }
  },
  "repos": {
    "github": 1096485,
    "gitlab": 3993,
    "bitbucket": 1219,
    "others": 14720
  },
  "stats": {
    "changes": 1526518,
    "inserts": 1117913,
    "updates": 208684,
    "deletes": 38545,
    "invalid": 161376,
    "ignored": 2
  },
  "batch": {
    "status": "killed",
    "limit": 29450,
    "since": 2749344,
    "index": 2770275,
    "until": 2778794,
    "started": "2021-10-17T00:49:50.641Z",
    "finished": "2021-10-17T06:35:16.054Z",
    "took_ms": 20725413,
    "found": 10310
  },
  "ignored": [
    2611203,
    2703386
  ]
}