{
  "error": false,
  "packages": 3378559,
  "last": 37828385,
  "latest": 37828385,
  "runs": {
    "total": 2095,
    "status": {
      "init": 1882,
      "timeout": 84,
      "killed": 127,
      "restart": 2
    }
  },
  "repos": {
    "unsets": 1394049,
    "github": 1949507,
    "gitlab": 6260,
    "bitbucket": 1384,
    "others": 27359
  },
  "stats": {
    "changes": 24245152,
    "inserts": 4737183,
    "updates": 17062341,
    "deletes": 1980031,
    "invalid": 465597,
    "ignored": 5
  },
  "batch": {
    "status": "init",
    "limit": 12996,
    "since": 37815389,
    "index": 37828385,
    "until": 37828385,
    "started": "2025-01-09T12:07:00.020Z",
    "finished": "2025-01-09T13:43:23.911Z",
    "took_ms": 5783891,
    "found": 9518
  },
  "ignored": [
    20012191,
    20468062,
    20908815,
    21553560,
    21660508
  ]
}