{
  "error": false,
  "packages": 2815567,
  "last": 31115795,
  "latest": 31115795,
  "runs": {
    "total": 1581,
    "status": {
      "init": 1371,
      "timeout": 82,
      "killed": 127,
      "restart": 1
    }
  },
  "repos": {
    "unsets": 1111557,
    "github": 1670949,
    "gitlab": 5919,
    "bitbucket": 1367,
    "others": 25775
  },
  "stats": {
    "changes": 18832412,
    "inserts": 3930019,
    "updates": 12790190,
    "deletes": 1721323,
    "invalid": 390880,
    "ignored": 5
  },
  "batch": {
    "status": "init",
    "limit": 10146,
    "since": 31105649,
    "index": 31115795,
    "until": 31115795,
    "started": "2024-04-26T00:14:35.368Z",
    "finished": "2024-04-26T02:29:07.434Z",
    "took_ms": 8072066,
    "found": 10126
  },
  "ignored": [
    20012191,
    20468062,
    20908815,
    21553560,
    21660508
  ]
}