{
  "error": false,
  "packages": 2061834,
  "last": 15377718,
  "latest": 15377718,
  "runs": {
    "total": 389,
    "status": {
      "init": 374,
      "timeout": 10,
      "killed": 5
    }
  },
  "repos": {
    "unsets": 757288,
    "github": 1279127,
    "gitlab": 4827,
    "bitbucket": 1310,
    "others": 19282
  },
  "stats": {
    "changes": 7777469,
    "inserts": 2094056,
    "updates": 5044334,
    "deletes": 472720,
    "invalid": 166359,
    "ignored": 0
  },
  "batch": {
    "status": "init",
    "limit": 7877,
    "since": 15369841,
    "index": 15377718,
    "until": 15377718,
    "started": "2022-08-24T12:05:24.810Z",
    "finished": "2022-08-24T14:16:18.364Z",
    "took_ms": 7853554,
    "found": 5032
  }
}