{
  "error": false,
  "packages": 2248791,
  "last": 19440696,
  "latest": 19440696,
  "runs": {
    "total": 719,
    "status": {
      "init": 690,
      "timeout": 22,
      "killed": 6,
      "restart": 1
    }
  },
  "repos": {
    "unsets": 842346,
    "github": 1378803,
    "gitlab": 5170,
    "bitbucket": 1334,
    "others": 21138
  },
  "stats": {
    "changes": 10124908,
    "inserts": 2306501,
    "updates": 7030199,
    "deletes": 544854,
    "invalid": 243354,
    "ignored": 0
  },
  "batch": {
    "status": "init",
    "limit": 6769,
    "since": 19433927,
    "index": 19440696,
    "until": 19440696,
    "started": "2023-02-05T12:04:48.049Z",
    "finished": "2023-02-05T13:59:08.900Z",
    "took_ms": 6860851,
    "found": 3486
  }
}