{
  "error": false,
  "packages": 2532361,
  "last": 26574137,
  "latest": 26588413,
  "runs": {
    "total": 1171,
    "status": {
      "init": 997,
      "timeout": 79,
      "killed": 94,
      "restart": 1
    }
  },
  "repos": {
    "unsets": 1012650,
    "github": 1489015,
    "gitlab": 5648,
    "bitbucket": 1361,
    "others": 23687
  },
  "stats": {
    "changes": 15165160,
    "inserts": 3452699,
    "updates": 9861253,
    "deletes": 1516560,
    "invalid": 334648,
    "ignored": 5
  },
  "batch": {
    "status": "init",
    "limit": 1,
    "since": 26574135,
    "index": 26574137,
    "until": 26574136,
    "started": "2023-09-29T12:05:16.245Z",
    "finished": "2023-09-29T12:05:26.995Z",
    "took_ms": 10750,
    "found": 1
  },
  "ignored": [
    20012191,
    20468062,
    20908815,
    21553560,
    21660508
  ]
}