{
  "error": false,
  "packages": 3069600,
  "last": 32194826,
  "latest": 32194826,
  "runs": {
    "total": 1667,
    "status": {
      "init": 1457,
      "timeout": 82,
      "killed": 127,
      "restart": 1
    }
  },
  "repos": {
    "unsets": 1249264,
    "github": 1786928,
    "gitlab": 5944,
    "bitbucket": 1370,
    "others": 26094
  },
  "stats": {
    "changes": 19873666,
    "inserts": 4233029,
    "updates": 13465552,
    "deletes": 1771011,
    "invalid": 404074,
    "ignored": 5
  },
  "batch": {
    "status": "init",
    "limit": 6313,
    "since": 32188513,
    "index": 32194826,
    "until": 32194826,
    "started": "2024-06-09T00:17:36.829Z",
    "finished": "2024-06-09T01:41:19.101Z",
    "took_ms": 5022272,
    "found": 6296
  },
  "ignored": [
    20012191,
    20468062,
    20908815,
    21553560,
    21660508
  ]
}