{
  "error": false,
  "packages": 1840411,
  "last": 8659916,
  "latest": 8659915,
  "runs": {
    "total": 143,
    "status": {
      "init": 139,
      "timeout": 2,
      "killed": 2
    }
  },
  "repos": {
    "unsets": 663146,
    "github": 1154972,
    "gitlab": 4356,
    "bitbucket": 1250,
    "others": 16687
  },
  "stats": {
    "changes": 3285398,
    "inserts": 1850436,
    "updates": 967693,
    "deletes": 398230,
    "invalid": 69039,
    "ignored": 0
  },
  "batch": {
    "status": "init",
    "limit": 12973,
    "since": 8646942,
    "index": 8659916,
    "until": 8659915,
    "started": "2022-02-21T12:25:08.549Z",
    "finished": "2022-02-21T13:29:04.739Z",
    "took_ms": 3836190,
    "found": 7109
  }
}