{
  "error": false,
  "packages": 1844304,
  "last": 8743120,
  "latest": 8743119,
  "runs": {
    "total": 149,
    "status": {
      "init": 145,
      "timeout": 2,
      "killed": 2
    }
  },
  "repos": {
    "unsets": 664959,
    "github": 1156994,
    "gitlab": 4372,
    "bitbucket": 1249,
    "others": 16730
  },
  "stats": {
    "changes": 3332318,
    "inserts": 1854818,
    "updates": 1007737,
    "deletes": 399807,
    "invalid": 69956,
    "ignored": 0
  },
  "batch": {
    "status": "init",
    "limit": 12382,
    "since": 8730737,
    "index": 8743120,
    "until": 8743119,
    "started": "2022-02-24T12:25:23.697Z",
    "finished": "2022-02-24T13:37:03.551Z",
    "took_ms": 4299854,
    "found": 7505
  }
}