{
  "packages": 970672,
  "last": 10944976,
  "latest": 10944976,
  "runs": {
    "total": 859,
    "status": {
      "restart": 4,
      "timeout": 67,
      "ok": 229,
      "killed": 559
    }
  },
  "repos": {
    "github": 954963,
    "gitlab": 3484,
    "bitbucket": 1160,
    "others": 11065
  },
  "stats": {
    "changes": 3795132,
    "inserts": 981851,
    "updates": 1476758,
    "deletes": 94592,
    "invalid": 1241931,
    "ignored": 14
  },
  "batch": {
    "limit": 7408,
    "since": 10937568,
    "index": 10944976,
    "until": 10944976,
    "started": "2020-12-29T16:43:34.782Z",
    "finished": "2020-12-29T21:32:19.245Z",
    "took_ms": 17324463,
    "found": 4202,
    "status": "ok"
  },
  "ignored": [
    2817133,
    2817134,
    5863655,
    5891749,
    6147589,
    6207043,
    6262717,
    6408267,
    6408268,
    6597446,
    6815143,
    6946259,
    7075370,
    7353196
  ]
}