{
  "error": false,
  "packages": 2000771,
  "last": 14652105,
  "latest": 14652104,
  "runs": {
    "total": 334,
    "status": {
      "init": 320,
      "timeout": 9,
      "killed": 5
    }
  },
  "repos": {
    "unsets": 742775,
    "github": 1232956,
    "gitlab": 4763,
    "bitbucket": 1303,
    "others": 18974
  },
  "stats": {
    "changes": 7339024,
    "inserts": 2029257,
    "updates": 4690237,
    "deletes": 460642,
    "invalid": 158888,
    "ignored": 0
  },
  "batch": {
    "status": "init",
    "limit": 11577,
    "since": 14640527,
    "index": 14652105,
    "until": 14652104,
    "started": "2022-07-27T12:05:21.472Z",
    "finished": "2022-07-27T14:09:04.349Z",
    "took_ms": 7422877,
    "found": 7450
  }
}