{
  "error": false,
  "packages": 3385549,
  "last": 33608596,
  "latest": 33608596,
  "runs": {
    "total": 1768,
    "status": {
      "init": 1557,
      "timeout": 83,
      "killed": 127,
      "restart": 1
    }
  },
  "repos": {
    "unsets": 1470075,
    "github": 1881631,
    "gitlab": 6035,
    "bitbucket": 1377,
    "others": 26431
  },
  "stats": {
    "changes": 21135763,
    "inserts": 4563086,
    "updates": 14367191,
    "deletes": 1787565,
    "invalid": 417921,
    "ignored": 5
  },
  "batch": {
    "status": "init",
    "limit": 13408,
    "since": 33595188,
    "index": 33608596,
    "until": 33608596,
    "started": "2024-07-30T00:16:22.785Z",
    "finished": "2024-07-30T02:02:23.966Z",
    "took_ms": 6361181,
    "found": 11307
  },
  "ignored": [
    20012191,
    20468062,
    20908815,
    21553560,
    21660508
  ]
}