{
  "packages": 843559,
  "last": 6100710,
  "latest": 6148315,
  "runs": {
    "total": 96,
    "status": {
      "restart": 4,
      "timeout": 24,
      "ok": 12,
      "killed": 56
    }
  },
  "repos": {
    "github": 830940,
    "gitlab": 2872,
    "bitbucket": 1060,
    "others": 8687
  },
  "stats": {
    "changes": 1478997,
    "inserts": 844564,
    "updates": 119891,
    "deletes": 46775,
    "invalid": 467767,
    "ignored": 4
  },
  "batch": {
    "limit": 1,
    "since": 6100708,
    "index": 6100710,
    "until": 6100709,
    "started": "2020-04-17T16:05:24.200Z",
    "finished": "2020-04-17T16:05:24.777Z",
    "took_ms": 577,
    "found": 1,
    "status": "ok"
  },
  "ignored": [
    2817133,
    2817134,
    5863655,
    5891749
  ]
}