{
  "packages": 987608,
  "last": 11620437,
  "latest": 11626012,
  "runs": {
    "total": 971,
    "status": {
      "restart": 4,
      "timeout": 72,
      "ok": 239,
      "killed": 656
    }
  },
  "repos": {
    "github": 971601,
    "gitlab": 3565,
    "bitbucket": 1185,
    "others": 11257
  },
  "stats": {
    "changes": 4116097,
    "inserts": 1000632,
    "updates": 1669597,
    "deletes": 104131,
    "invalid": 1341737,
    "ignored": 14
  },
  "batch": {
    "limit": 8779,
    "since": 11617233,
    "index": 11620437,
    "until": 11626012,
    "started": "2021-02-05T00:45:21.789Z",
    "finished": "2021-02-05T05:45:26.162Z",
    "took_ms": 18004373,
    "found": 1600,
    "status": "killed"
  },
  "ignored": [
    2817133,
    2817134,
    5863655,
    5891749,
    6147589,
    6207043,
    6262717,
    6408267,
    6408268,
    6597446,
    6815143,
    6946259,
    7075370,
    7353196
  ]
}