{
  "packages": 972488,
  "last": 10999433,
  "latest": 11014067,
  "runs": {
    "total": 877,
    "status": {
      "restart": 4,
      "timeout": 67,
      "ok": 229,
      "killed": 577
    }
  },
  "repos": {
    "github": 956752,
    "gitlab": 3490,
    "bitbucket": 1161,
    "others": 11085
  },
  "stats": {
    "changes": 3821384,
    "inserts": 983849,
    "updates": 1492483,
    "deletes": 95365,
    "invalid": 1249687,
    "ignored": 14
  },
  "batch": {
    "limit": 29107,
    "since": 10984960,
    "index": 10999433,
    "until": 11014067,
    "started": "2021-01-04T16:45:43.013Z",
    "finished": "2021-01-04T21:45:50.671Z",
    "took_ms": 18007658,
    "found": 5008,
    "status": "killed"
  },
  "ignored": [
    2817133,
    2817134,
    5863655,
    5891749,
    6147589,
    6207043,
    6262717,
    6408267,
    6408268,
    6597446,
    6815143,
    6946259,
    7075370,
    7353196
  ]
}