{
  "packages": 1094998,
  "last": 16000181,
  "latest": 16039540,
  "runs": {
    "total": 1583,
    "status": {
      "restart": 4,
      "timeout": 108,
      "ok": 285,
      "killed": 1186
    }
  },
  "repos": {
    "github": 1075413,
    "gitlab": 4059,
    "bitbucket": 1250,
    "others": 14276
  },
  "stats": {
    "changes": 6140958,
    "inserts": 1117399,
    "updates": 2814358,
    "deletes": 254623,
    "invalid": 1954578,
    "ignored": 15
  },
  "batch": {
    "limit": 55682,
    "since": 15983858,
    "index": 16000181,
    "until": 16039540,
    "started": "2021-08-28T16:27:53.590Z",
    "finished": "2021-08-28T21:28:11.365Z",
    "took_ms": 18017775,
    "found": 5972,
    "status": "killed"
  },
  "ignored": [
    2817133,
    2817134,
    5863655,
    5891749,
    6147589,
    6207043,
    6262717,
    6408267,
    6408268,
    6597446,
    6815143,
    6946259,
    7075370,
    7353196,
    12841535
  ]
}