{
  "packages": 1036515,
  "last": 13501577,
  "latest": 13510292,
  "runs": {
    "total": 1244,
    "status": {
      "restart": 4,
      "timeout": 86,
      "ok": 263,
      "killed": 891
    }
  },
  "repos": {
    "github": 1019203,
    "gitlab": 3739,
    "bitbucket": 1221,
    "others": 12352
  },
  "stats": {
    "changes": 5055369,
    "inserts": 1053595,
    "updates": 2214330,
    "deletes": 150225,
    "invalid": 1637219,
    "ignored": 15
  },
  "batch": {
    "limit": 22196,
    "since": 13488096,
    "index": 13501577,
    "until": 13510292,
    "started": "2021-05-07T08:25:29.093Z",
    "finished": "2021-05-07T13:25:30.493Z",
    "took_ms": 18001400,
    "found": 5406,
    "status": "killed"
  },
  "ignored": [
    2817133,
    2817134,
    5863655,
    5891749,
    6147589,
    6207043,
    6262717,
    6408267,
    6408268,
    6597446,
    6815143,
    6946259,
    7075370,
    7353196,
    12841535
  ]
}