{
  "error": false,
  "packages": 3216581,
  "last": 32800556,
  "latest": 32800556,
  "runs": {
    "total": 1715,
    "status": {
      "init": 1505,
      "timeout": 82,
      "killed": 127,
      "restart": 1
    }
  },
  "repos": {
    "unsets": 1345925,
    "github": 1837008,
    "gitlab": 5995,
    "bitbucket": 1373,
    "others": 26280
  },
  "stats": {
    "changes": 20447067,
    "inserts": 4388047,
    "updates": 13868397,
    "deletes": 1779779,
    "invalid": 410844,
    "ignored": 5
  },
  "batch": {
    "status": "init",
    "limit": 20421,
    "since": 32780135,
    "index": 32800556,
    "until": 32800556,
    "started": "2024-07-03T12:06:05.988Z",
    "finished": "2024-07-03T13:43:54.476Z",
    "took_ms": 5868488,
    "found": 19510
  },
  "ignored": [
    20012191,
    20468062,
    20908815,
    21553560,
    21660508
  ]
}