{
  "packages": 980174,
  "last": 11300866,
  "latest": 11314292,
  "runs": {
    "total": 925,
    "status": {
      "restart": 4,
      "timeout": 69,
      "ok": 234,
      "killed": 618
    }
  },
  "repos": {
    "github": 964263,
    "gitlab": 3502,
    "bitbucket": 1178,
    "others": 11231
  },
  "stats": {
    "changes": 3962230,
    "inserts": 992349,
    "updates": 1575948,
    "deletes": 99749,
    "invalid": 1294184,
    "ignored": 14
  },
  "batch": {
    "limit": 19558,
    "since": 11294734,
    "index": 11300866,
    "until": 11314292,
    "started": "2021-01-20T17:04:26.132Z",
    "finished": "2021-01-20T22:04:51.093Z",
    "took_ms": 18024961,
    "found": 2939,
    "status": "killed"
  },
  "ignored": [
    2817133,
    2817134,
    5863655,
    5891749,
    6147589,
    6207043,
    6262717,
    6408267,
    6408268,
    6597446,
    6815143,
    6946259,
    7075370,
    7353196
  ]
}