{
  "packages": 830204,
  "last": 5643875,
  "latest": 5657958,
  "runs": {
    "total": 17,
    "status": {
      "restart": 4,
      "timeout": 4,
      "ok": 2,
      "killed": 7
    }
  },
  "repos": {
    "github": 817914,
    "gitlab": 2770,
    "bitbucket": 1050,
    "others": 8470
  },
  "stats": {
    "changes": 1285709,
    "inserts": 830265,
    "updates": 9836,
    "deletes": 42254,
    "invalid": 403354,
    "ignored": 2
  },
  "batch": {
    "limit": 1,
    "since": 5643875,
    "index": 5643875,
    "until": 5643876,
    "started": "2020-03-21T16:05:52.088Z",
    "finished": "2020-03-21T21:06:22.009Z",
    "took_ms": 18029921,
    "found": 0,
    "status": "killed"
  },
  "ignored": [
    2817133,
    2817134
  ]
}