{
  "error": false,
  "packages": 2078372,
  "last": 15757661,
  "latest": 15757661,
  "runs": {
    "total": 421,
    "status": {
      "init": 406,
      "timeout": 10,
      "killed": 5
    }
  },
  "repos": {
    "unsets": 766136,
    "github": 1286601,
    "gitlab": 4848,
    "bitbucket": 1318,
    "others": 19469
  },
  "stats": {
    "changes": 8012972,
    "inserts": 2112676,
    "updates": 5250056,
    "deletes": 479075,
    "invalid": 171165,
    "ignored": 0
  },
  "batch": {
    "status": "init",
    "limit": 11750,
    "since": 15745911,
    "index": 15757661,
    "until": 15757661,
    "started": "2022-09-09T12:06:02.983Z",
    "finished": "2022-09-09T14:11:28.926Z",
    "took_ms": 7525943,
    "found": 10974
  }
}