{
  "error": false,
  "packages": 2242279,
  "last": 19080069,
  "latest": 19080068,
  "runs": {
    "total": 696,
    "status": {
      "init": 668,
      "timeout": 21,
      "killed": 6,
      "restart": 1
    }
  },
  "repos": {
    "unsets": 835027,
    "github": 1379732,
    "gitlab": 5148,
    "bitbucket": 1335,
    "others": 21037
  },
  "stats": {
    "changes": 9913404,
    "inserts": 2292395,
    "updates": 6878539,
    "deletes": 535278,
    "invalid": 207192,
    "ignored": 0
  },
  "batch": {
    "status": "init",
    "limit": 19740,
    "since": 19060328,
    "index": 19080069,
    "until": 19080068,
    "started": "2023-01-25T00:15:15.953Z",
    "finished": "2023-01-25T03:54:22.219Z",
    "took_ms": 13146266,
    "found": 15340
  }
}