{
  "error": false,
  "packages": 2080851,
  "last": 15805773,
  "latest": 15805772,
  "runs": {
    "total": 427,
    "status": {
      "init": 412,
      "timeout": 10,
      "killed": 5
    }
  },
  "repos": {
    "unsets": 767432,
    "github": 1287796,
    "gitlab": 4852,
    "bitbucket": 1319,
    "others": 19452
  },
  "stats": {
    "changes": 8040276,
    "inserts": 2115487,
    "updates": 5272548,
    "deletes": 480532,
    "invalid": 171709,
    "ignored": 0
  },
  "batch": {
    "status": "init",
    "limit": 10342,
    "since": 15795430,
    "index": 15805773,
    "until": 15805772,
    "started": "2022-09-12T12:06:58.659Z",
    "finished": "2022-09-12T13:43:35.553Z",
    "took_ms": 5796894,
    "found": 5845
  }
}