{
  "error": false,
  "packages": 3303725,
  "last": 34632658,
  "latest": 34632658,
  "runs": {
    "total": 1837,
    "status": {
      "init": 1626,
      "timeout": 83,
      "killed": 127,
      "restart": 1
    }
  },
  "repos": {
    "unsets": 1361284,
    "github": 1908176,
    "gitlab": 6139,
    "bitbucket": 1377,
    "others": 26749
  },
  "stats": {
    "changes": 21984629,
    "inserts": 4610649,
    "updates": 15027344,
    "deletes": 1918551,
    "invalid": 428085,
    "ignored": 5
  },
  "batch": {
    "status": "init",
    "limit": 13278,
    "since": 34619380,
    "index": 34632658,
    "until": 34632658,
    "started": "2024-09-02T12:06:55.866Z",
    "finished": "2024-09-02T13:24:08.615Z",
    "took_ms": 4632749,
    "found": 10531
  },
  "ignored": [
    20012191,
    20468062,
    20908815,
    21553560,
    21660508
  ]
}