{
  "error": false,
  "packages": 1818180,
  "last": 8132438,
  "latest": 8132438,
  "runs": {
    "total": 107,
    "status": {
      "init": 103,
      "timeout": 2,
      "killed": 2
    }
  },
  "repos": {
    "unsets": 651669,
    "github": 1144588,
    "gitlab": 4291,
    "bitbucket": 1242,
    "others": 16390
  },
  "stats": {
    "changes": 3001872,
    "inserts": 1825501,
    "updates": 726963,
    "deletes": 386380,
    "invalid": 63028,
    "ignored": 0
  },
  "batch": {
    "status": "init",
    "limit": 5006,
    "since": 8127432,
    "index": 8132438,
    "until": 8132438,
    "started": "2022-01-30T12:21:36.053Z",
    "finished": "2022-01-30T13:05:40.221Z",
    "took_ms": 2644168,
    "found": 2685
  }
}