{
  "error": false,
  "packages": 2063667,
  "last": 15417254,
  "latest": 15417251,
  "runs": {
    "total": 392,
    "status": {
      "init": 377,
      "timeout": 10,
      "killed": 5
    }
  },
  "repos": {
    "unsets": 758298,
    "github": 1279930,
    "gitlab": 4834,
    "bitbucket": 1310,
    "others": 19295
  },
  "stats": {
    "changes": 7806069,
    "inserts": 2096136,
    "updates": 5069666,
    "deletes": 473101,
    "invalid": 167166,
    "ignored": 0
  },
  "batch": {
    "status": "init",
    "limit": 15803,
    "since": 15401448,
    "index": 15417254,
    "until": 15417251,
    "started": "2022-08-26T00:16:44.322Z",
    "finished": "2022-08-26T02:44:21.368Z",
    "took_ms": 8857046,
    "found": 9211
  }
}