{
  "error": false,
  "packages": 2541106,
  "last": 26807532,
  "latest": 26825252,
  "runs": {
    "total": 1194,
    "status": {
      "init": 1012,
      "timeout": 79,
      "killed": 102,
      "restart": 1
    }
  },
  "repos": {
    "unsets": 1017177,
    "github": 1493149,
    "gitlab": 5657,
    "bitbucket": 1354,
    "others": 23769
  },
  "stats": {
    "changes": 15306854,
    "inserts": 3462845,
    "updates": 9988104,
    "deletes": 1518782,
    "invalid": 337123,
    "ignored": 5
  },
  "batch": {
    "status": "init",
    "limit": 1,
    "since": 26807531,
    "index": 26807532,
    "until": 26807532,
    "started": "2023-10-11T00:13:49.826Z",
    "finished": "2023-10-11T00:15:40.416Z",
    "took_ms": 110590,
    "found": 1
  },
  "ignored": [
    20012191,
    20468062,
    20908815,
    21553560,
    21660508
  ]
}