{
  "error": false,
  "packages": 1969838,
  "last": 13977483,
  "latest": 13977483,
  "runs": {
    "total": 276,
    "status": {
      "init": 265,
      "timeout": 6,
      "killed": 5
    }
  },
  "repos": {
    "unsets": 727419,
    "github": 1217888,
    "gitlab": 4688,
    "bitbucket": 1298,
    "others": 18545
  },
  "stats": {
    "changes": 6909908,
    "inserts": 1993126,
    "updates": 4318373,
    "deletes": 448295,
    "invalid": 150114,
    "ignored": 0
  },
  "batch": {
    "status": "init",
    "limit": 17864,
    "since": 13959619,
    "index": 13977483,
    "until": 13977483,
    "started": "2022-06-28T12:34:53.979Z",
    "finished": "2022-06-28T14:43:58.187Z",
    "took_ms": 7744208,
    "found": 15804
  }
}