{
  "error": false,
  "packages": 2555714,
  "last": 27321464,
  "latest": 27336324,
  "runs": {
    "total": 1244,
    "status": {
      "init": 1040,
      "timeout": 81,
      "killed": 122,
      "restart": 1
    }
  },
  "repos": {
    "unsets": 1021869,
    "github": 1502745,
    "gitlab": 5708,
    "bitbucket": 1354,
    "others": 24038
  },
  "stats": {
    "changes": 15646584,
    "inserts": 3487398,
    "updates": 10285999,
    "deletes": 1530109,
    "invalid": 343078,
    "ignored": 5
  },
  "batch": {
    "status": "init",
    "limit": 1,
    "since": 27321463,
    "index": 27321464,
    "until": 27321464,
    "started": "2023-11-05T00:15:08.399Z",
    "finished": "2023-11-05T00:15:31.642Z",
    "took_ms": 23243,
    "found": 1
  },
  "ignored": [
    20012191,
    20468062,
    20908815,
    21553560,
    21660508
  ]
}