{
  "error": false,
  "packages": 3394834,
  "last": 38282908,
  "latest": 38282908,
  "runs": {
    "total": 2149,
    "status": {
      "init": 1934,
      "timeout": 84,
      "killed": 129,
      "restart": 2
    }
  },
  "repos": {
    "unsets": 1402316,
    "github": 1957424,
    "gitlab": 6270,
    "bitbucket": 1382,
    "others": 27442
  },
  "stats": {
    "changes": 24527884,
    "inserts": 4758446,
    "updates": 17311122,
    "deletes": 1987794,
    "invalid": 470522,
    "ignored": 6
  },
  "batch": {
    "status": "init",
    "limit": 16121,
    "since": 38266787,
    "index": 38282908,
    "until": 38282908,
    "started": "2025-02-06T00:18:53.004Z",
    "finished": "2025-02-06T01:26:43.450Z",
    "took_ms": 4070446,
    "found": 10180
  },
  "ignored": [
    20012191,
    20468062,
    20908815,
    21553560,
    21660508,
    38167386
  ]
}