{
  "packages": 953114,
  "last": 10304137,
  "latest": 10328802,
  "runs": {
    "total": 757,
    "status": {
      "restart": 4,
      "timeout": 65,
      "ok": 203,
      "killed": 485
    }
  },
  "repos": {
    "github": 937923,
    "gitlab": 3357,
    "bitbucket": 1144,
    "others": 10690
  },
  "stats": {
    "changes": 3480998,
    "inserts": 962884,
    "updates": 1283649,
    "deletes": 87867,
    "invalid": 1146598,
    "ignored": 14
  },
  "batch": {
    "limit": 24665,
    "since": 10304137,
    "index": 10304137,
    "until": 10328802,
    "started": "2020-11-25T08:17:56.286Z",
    "finished": "2020-11-25T13:18:20.255Z",
    "took_ms": 18023969,
    "found": 0,
    "status": "killed"
  },
  "ignored": [
    2817133,
    2817134,
    5863655,
    5891749,
    6147589,
    6207043,
    6262717,
    6408267,
    6408268,
    6597446,
    6815143,
    6946259,
    7075370,
    7353196
  ]
}