{
  "error": false,
  "packages": 1776961,
  "last": 7124171,
  "latest": 7124171,
  "runs": {
    "total": 39,
    "status": {
      "init": 35,
      "timeout": 2,
      "killed": 2
    }
  },
  "repos": {
    "unsets": 631105,
    "github": 1124736,
    "gitlab": 4154,
    "bitbucket": 1234,
    "others": 15732
  },
  "stats": {
    "changes": 2421274,
    "inserts": 1779507,
    "updates": 226354,
    "deletes": 364828,
    "invalid": 50585,
    "ignored": 0
  },
  "batch": {
    "status": "init",
    "limit": 12644,
    "since": 7111527,
    "index": 7124171,
    "until": 7124171,
    "started": "2021-12-18T00:54:46.459Z",
    "finished": "2021-12-18T02:29:17.440Z",
    "took_ms": 5670981,
    "found": 7169
  }
}