{
  "error": false,
  "packages": 2259249,
  "last": 19646076,
  "latest": 19646076,
  "runs": {
    "total": 734,
    "status": {
      "init": 705,
      "timeout": 22,
      "killed": 6,
      "restart": 1
    }
  },
  "repos": {
    "unsets": 846623,
    "github": 1384859,
    "gitlab": 5192,
    "bitbucket": 1339,
    "others": 21236
  },
  "stats": {
    "changes": 10246598,
    "inserts": 2319991,
    "updates": 7131352,
    "deletes": 549706,
    "invalid": 245549,
    "ignored": 0
  },
  "batch": {
    "status": "init",
    "limit": 12114,
    "since": 19633962,
    "index": 19646076,
    "until": 19646076,
    "started": "2023-02-13T00:15:44.410Z",
    "finished": "2023-02-13T01:43:58.668Z",
    "took_ms": 5294258,
    "found": 5417
  }
}