{
  "error": true,
  "packages": 3202832,
  "last": 23089082,
  "latest": 23102054,
  "runs": {
    "total": 917,
    "status": {
      "init": 825,
      "timeout": 59,
      "killed": 32,
      "restart": 1
    }
  },
  "repos": {
    "unsets": 1730566,
    "github": 1443114,
    "gitlab": 5398,
    "bitbucket": 1348,
    "others": 22406
  },
  "stats": {
    "changes": 12630652,
    "inserts": 3320230,
    "updates": 8322776,
    "deletes": 684969,
    "invalid": 302677,
    "ignored": 5
  },
  "batch": {
    "status": "killed",
    "limit": 38274,
    "since": 23063780,
    "index": 23089082,
    "until": 23102054,
    "started": "2023-05-25T00:14:08.828Z",
    "finished": "2023-05-25T05:59:09.105Z",
    "took_ms": 20700277,
    "found": 12619
  },
  "ignored": [
    20012191,
    20468062,
    20908815,
    21553560,
    21660508
  ]
}