{
  "error": false,
  "packages": 3205520,
  "last": 23175555,
  "latest": 23198269,
  "runs": {
    "total": 926,
    "status": {
      "init": 830,
      "timeout": 61,
      "killed": 34,
      "restart": 1
    }
  },
  "repos": {
    "unsets": 1731763,
    "github": 1444571,
    "gitlab": 5402,
    "bitbucket": 1348,
    "others": 22436
  },
  "stats": {
    "changes": 12675477,
    "inserts": 3324041,
    "updates": 8361509,
    "deletes": 686516,
    "invalid": 303411,
    "ignored": 5
  },
  "batch": {
    "status": "init",
    "limit": 1,
    "since": 23175553,
    "index": 23175555,
    "until": 23175554,
    "started": "2023-05-29T12:05:15.749Z",
    "finished": "2023-05-29T12:13:39.269Z",
    "took_ms": 503520,
    "found": 1
  },
  "ignored": [
    20012191,
    20468062,
    20908815,
    21553560,
    21660508
  ]
}