{
  "error": false,
  "packages": 3348018,
  "last": 36872831,
  "latest": 36872831,
  "runs": {
    "total": 2011,
    "status": {
      "init": 1798,
      "timeout": 84,
      "killed": 127,
      "restart": 2
    }
  },
  "repos": {
    "unsets": 1376815,
    "github": 1936462,
    "gitlab": 6236,
    "bitbucket": 1379,
    "others": 27126
  },
  "stats": {
    "changes": 23601667,
    "inserts": 4698154,
    "updates": 16481507,
    "deletes": 1967672,
    "invalid": 454334,
    "ignored": 5
  },
  "batch": {
    "status": "init",
    "limit": 7860,
    "since": 36864971,
    "index": 36872831,
    "until": 36872831,
    "started": "2024-11-28T12:07:39.360Z",
    "finished": "2024-11-28T13:13:27.097Z",
    "took_ms": 3947737,
    "found": 6481
  },
  "ignored": [
    20012191,
    20468062,
    20908815,
    21553560,
    21660508
  ]
}