{
  "error": false,
  "packages": 3363643,
  "last": 37365077,
  "latest": 37365076,
  "runs": {
    "total": 2052,
    "status": {
      "init": 1839,
      "timeout": 84,
      "killed": 127,
      "restart": 2
    }
  },
  "repos": {
    "unsets": 1386029,
    "github": 1942733,
    "gitlab": 6251,
    "bitbucket": 1383,
    "others": 27247
  },
  "stats": {
    "changes": 23960341,
    "inserts": 4718704,
    "updates": 16806326,
    "deletes": 1974031,
    "invalid": 461280,
    "ignored": 5
  },
  "batch": {
    "status": "init",
    "limit": 18636,
    "since": 37346440,
    "index": 37365077,
    "until": 37365076,
    "started": "2024-12-19T00:19:48.118Z",
    "finished": "2024-12-19T02:13:55.933Z",
    "took_ms": 6847815,
    "found": 12531
  },
  "ignored": [
    20012191,
    20468062,
    20908815,
    21553560,
    21660508
  ]
}