{
  "error": false,
  "packages": 2721210,
  "last": 30202914,
  "latest": 30202914,
  "runs": {
    "total": 1528,
    "status": {
      "init": 1319,
      "timeout": 82,
      "killed": 126,
      "restart": 1
    }
  },
  "repos": {
    "unsets": 1081064,
    "github": 1607410,
    "gitlab": 5899,
    "bitbucket": 1366,
    "others": 25471
  },
  "stats": {
    "changes": 17992758,
    "inserts": 3692354,
    "updates": 12340729,
    "deletes": 1576709,
    "invalid": 382966,
    "ignored": 5
  },
  "batch": {
    "status": "init",
    "limit": 12181,
    "since": 30190733,
    "index": 30202914,
    "until": 30202914,
    "started": "2024-03-26T00:13:53.910Z",
    "finished": "2024-03-26T02:39:21.360Z",
    "took_ms": 8727450,
    "found": 11831
  },
  "ignored": [
    20012191,
    20468062,
    20908815,
    21553560,
    21660508
  ]
}