{
  "error": false,
  "packages": 2627372,
  "last": 29078501,
  "latest": 29078501,
  "runs": {
    "total": 1427,
    "status": {
      "init": 1218,
      "timeout": 82,
      "killed": 126,
      "restart": 1
    }
  },
  "repos": {
    "unsets": 1059432,
    "github": 1535779,
    "gitlab": 5833,
    "bitbucket": 1364,
    "others": 24964
  },
  "stats": {
    "changes": 17068237,
    "inserts": 3580182,
    "updates": 11565451,
    "deletes": 1555376,
    "invalid": 367228,
    "ignored": 5
  },
  "batch": {
    "status": "init",
    "limit": 8027,
    "since": 29070474,
    "index": 29078501,
    "until": 29078501,
    "started": "2024-02-04T12:05:04.782Z",
    "finished": "2024-02-04T13:00:02.375Z",
    "took_ms": 3297593,
    "found": 4641
  },
  "ignored": [
    20012191,
    20468062,
    20908815,
    21553560,
    21660508
  ]
}