{
  "packages": 994505,
  "last": 11936875,
  "latest": 11936870,
  "runs": {
    "total": 1016,
    "status": {
      "restart": 4,
      "timeout": 74,
      "ok": 242,
      "killed": 696
    }
  },
  "repos": {
    "github": 978378,
    "gitlab": 3582,
    "bitbucket": 1189,
    "others": 11356
  },
  "stats": {
    "changes": 4272082,
    "inserts": 1008248,
    "updates": 1760403,
    "deletes": 115970,
    "invalid": 1387461,
    "ignored": 14
  },
  "batch": {
    "limit": 5838,
    "since": 11931032,
    "index": 11936875,
    "until": 11936870,
    "started": "2021-02-20T08:22:01.629Z",
    "finished": "2021-02-20T10:47:09.185Z",
    "took_ms": 8707556,
    "found": 3481,
    "status": "ok"
  },
  "ignored": [
    2817133,
    2817134,
    5863655,
    5891749,
    6147589,
    6207043,
    6262717,
    6408267,
    6408268,
    6597446,
    6815143,
    6946259,
    7075370,
    7353196
  ]
}